.gitignore
.landscape.yml
CHANGES.txt
LICENSE
MANIFEST.in
README.rst
docs_requirements.txt
setup.py
docs/Makefile
docs/make.bat
docs/source/conf.py
docs/source/index.rst
docs/source/ssh_paramiko.rst
ssh_paramiko/__init__.py
ssh_paramiko/ssh_paramiko.py
ssh_paramiko.egg-info/PKG-INFO
ssh_paramiko.egg-info/SOURCES.txt
ssh_paramiko.egg-info/dependency_links.txt
ssh_paramiko.egg-info/requires.txt
ssh_paramiko.egg-info/top_level.txt