Metadata-Version: 1.1
Name: ssh_paramiko
Version: 0.1.2
Summary: Wrapper ssh using paramiko to interact with remote servers
Home-page: https://github.com/jonDel/ssh_paramiko
Author: Jonatan Dellagostin
Author-email: jdellagostin@gmail.com
License: GPLv3
Keywords: ssh secure sftp ftp shell remote paramiko
Platform: UNKNOWN
Classifier: Development Status :: 3 - Alpha
Classifier: License :: OSI Approved :: GNU General Public License v3 (GPLv3)
Classifier: Programming Language :: Python :: 2.6
Classifier: Programming Language :: Python :: 2.7
Classifier: Topic :: System :: Networking
Classifier: Topic :: System :: Systems Administration
Classifier: Topic :: Internet :: File Transfer Protocol (FTP)
Classifier: Topic :: System :: Shells
